doapi/__init__.py
doapi/action.py
doapi/base.py
doapi/doapi.py
doapi/domain.py
doapi/droplet.py
doapi/floating_ip.py
doapi/image.py
doapi/ssh_key.py
doapi/tag.py
doapi/cli/__init__.py
doapi/cli/_util.py
doapi/cli/account.py
doapi/cli/action.py
doapi/cli/domain.py
doapi/cli/droplet.py
doapi/cli/floating_ip.py
doapi/cli/image.py
doapi/cli/region.py
doapi/cli/request.py
doapi/cli/size.py
doapi/cli/ssh_key.py
doapi/cli/tag.py
doapi-0.2.0.dist-info/DESCRIPTION.rst
doapi-0.2.0.dist-info/METADATA
doapi-0.2.0.dist-info/RECORD
doapi-0.2.0.dist-info/WHEEL
doapi-0.2.0.dist-info/entry_points.txt
doapi-0.2.0.dist-info/metadata.json
doapi-0.2.0.dist-info/top_level.txt
