Metadata-Version: 2.0
Name: doapi
Version: 0.2.0
Summary: DigitalOcean API library & CLI
Home-page: https://github.com/jwodder/doapi
Author: John Thorvald Wodder II
Author-email: doapi@varonathe.org
License: MIT
Keywords: DigitalOcean Digital Ocean cloud
Platform: UNKNOWN
Classifier: Development Status :: 4 - Beta
Classifier: Programming Language :: Python :: 2
Classifier: Programming Language :: Python :: 2.7
Classifier: License :: OSI Approved :: MIT License
Classifier: Environment :: Console
Classifier: Intended Audience :: Developers
Classifier: Intended Audience :: Information Technology
Classifier: Intended Audience :: System Administrators
Classifier: Topic :: Internet
Classifier: Topic :: Internet :: Name Service (DNS)
Classifier: Topic :: System :: Systems Administration
Requires-Dist: pyRFC3339 (>=1.0,<2)
Requires-Dist: requests (<3,>=2.2.0)
Requires-Dist: six (>=1.5.0,<2)
